pod_feeder_v2/__init__.py
pod_feeder_v2/clean_db.py
pod_feeder_v2/pod_feeder.py
tests/__init__.py
tests/test_pod_feeder.py
pod_feeder_v2-1.0.9.dist-info/LICENSE
pod_feeder_v2-1.0.9.dist-info/METADATA
pod_feeder_v2-1.0.9.dist-info/WHEEL
pod_feeder_v2-1.0.9.dist-info/entry_points.txt
pod_feeder_v2-1.0.9.dist-info/top_level.txt
pod_feeder_v2-1.0.9.dist-info/RECORD
