Metadata-Version: 2.1
Name: pod-feeder-v2
Version: 1.0.9
Summary: A utility to publish RSS/Atom feeds to Diaspora*
Home-page: https://gitlab.com/brianodonnell/pod_feeder_v2
Author: Brian Ó
Author-email: brian@pancrypticon.net
Keywords: atom bot diaspora feeds newsfeeds rss social syndication
Classifier: Programming Language :: Python :: 3
Classifier: License :: OSI Approved :: MIT License
Classifier: Operating System :: OS Independent
Requires-Python: >=3.9
License-File: LICENSE
Requires-Dist: diaspy-api
Requires-Dist: feedparser
Requires-Dist: html2text
Requires-Dist: urllib3
